froog/__init__.py
froog/gradient.py
froog/ops.py
froog/optim.py
froog/tensor.py
froog/utils.py
froog-0.5.2.dist-info/METADATA
froog-0.5.2.dist-info/WHEEL
froog-0.5.2.dist-info/top_level.txt
froog-0.5.2.dist-info/RECORD
