Metadata-Version: 2.1
Name: froog
Version: 0.5.2
Summary: tensor library with opencl and metal support
Author: Kevin Buhler
License: MIT
Classifier: Programming Language :: Python :: 3
Classifier: License :: OSI Approved :: MIT License
Requires-Python: >=3.8
Requires-Dist: numpy
Requires-Dist: requests
Requires-Dist: matplotlib
